bonuspay/__init__.py
bonuspay/__main__.py
bonuspay/account.py
bonuspay/common.py
bonuspay/fx_rate.py
bonuspay/payment.py
bonuspay/server.py
bonuspay/topup.py
bonuspay/withdraw.py
mcp_bonuspay-0.1.3.dist-info/METADATA
mcp_bonuspay-0.1.3.dist-info/WHEEL
mcp_bonuspay-0.1.3.dist-info/entry_points.txt
mcp_bonuspay-0.1.3.dist-info/RECORD
