Metadata-Version: 2.4
Name: mcp-bonuspay
Version: 0.1.3
Summary: MCP Server for BonusPay API.
Author-email: gavin <meiyan532484710@gmail.com>
Requires-Python: >=3.10
Requires-Dist: cryptography>=42.0.3
Requires-Dist: httpx-sse>=0.4.1
Requires-Dist: httpx>=0.28.1
Requires-Dist: mcp[cli]>=1.15.0
Requires-Dist: python-dotenv>=1.1.1
Requires-Dist: typer>=0.16.0
